lkmongoprovider/__init__.py
lkmongoprovider/provider.py
lkmongodbprovider-0.1.dist-info/METADATA
lkmongodbprovider-0.1.dist-info/WHEEL
lkmongodbprovider-0.1.dist-info/top_level.txt
lkmongodbprovider-0.1.dist-info/RECORD
